piscada_foresight/__init__.py
piscada_foresight/data.py
piscada_foresight/domains.py
piscada_foresight/http_piscada.py
piscada_foresight/model.py
piscada_foresight/py.typed
piscada_foresight/parser_graphql_to_df/time_series/__init__.py
piscada_foresight/parser_graphql_to_df/time_series/timeseries_response_parser.py
piscada_foresight/queries_templates/README.md
piscada_foresight/queries_templates/__init__.py
piscada_foresight/queries_templates/query_handler.py
piscada_foresight/queries_templates/query_manager.py
piscada_foresight/queries_templates/graphql_queries/domains/get_domains.graphql
piscada_foresight/queries_templates/graphql_queries/timeseries/get_aggregated_values.j2
piscada_foresight/queries_templates/graphql_queries/timeseries/get_latest_value.j2
piscada_foresight/queries_templates/graphql_queries/timeseries/get_latest_values.j2
piscada_foresight/queries_templates/graphql_queries/timeseries/get_raw_values.j2
piscada_foresight-0.6.5.dist-info/METADATA
piscada_foresight-0.6.5.dist-info/WHEEL
piscada_foresight-0.6.5.dist-info/RECORD
