Metadata-Version: 2.4
Name: piscada-foresight
Version: 0.6.5
Summary: Library for Piscada Foresight; Access knowledge-graph and timeseries data.
Author-email: Tim Jagenberg <tim.jagenberg@piscada.com>, Filip Henrik Larsen <filip.larsen@piscada.com>, Robin Vacher <robin.vacher@piscada.com>
Requires-Python: >=3.12
Requires-Dist: authlib>=1.3.2
Requires-Dist: gql[httpx]>=3.5.0
Requires-Dist: jinja2==3.1.4
Requires-Dist: pandas>=2.2.3
Requires-Dist: pydantic>=2.9.2
